ieee_2030_5/__main__.py
ieee_2030_5/adapters/__init__.py
ieee_2030_5/adapters/adapters.py
ieee_2030_5/adapters/gridappsd_adapter.py
ieee_2030_5/basic_proxy.py
ieee_2030_5/certs.py
ieee_2030_5/client/__init__.py
ieee_2030_5/client/client.py
ieee_2030_5/config.py
ieee_2030_5/config_setup.py
ieee_2030_5/control.py
ieee_2030_5/data/__init__.py
ieee_2030_5/data/indexer.py
ieee_2030_5/execute.py
ieee_2030_5/flask_server.py
ieee_2030_5/gridappsd-2030_5.code-workspace
ieee_2030_5/hrefs.py
ieee_2030_5/models/Config.py
ieee_2030_5/models/__init__.py
ieee_2030_5/models/constants.py
ieee_2030_5/models/derforecasts.py
ieee_2030_5/models/enums.py
ieee_2030_5/models/output/__init__.py
ieee_2030_5/models/output/output_models.py
ieee_2030_5/models/sep.py
ieee_2030_5/models/tree.py
ieee_2030_5/persistance/__init__.py
ieee_2030_5/persistance/points.py
ieee_2030_5/server/__init__.py
ieee_2030_5/server/admin_endpoints.py
ieee_2030_5/server/base_request.py
ieee_2030_5/server/dcapfs.py
ieee_2030_5/server/derfs.py
ieee_2030_5/server/enddevicesfs.py
ieee_2030_5/server/exceptions.py
ieee_2030_5/server/logfs.py
ieee_2030_5/server/meteringfs.py
ieee_2030_5/server/server_constructs.py
ieee_2030_5/server/server_endpoints.py
ieee_2030_5/server/timefs.py
ieee_2030_5/server/usage_pointfs.py
ieee_2030_5/server/uuid_handler.py
ieee_2030_5/service.py
ieee_2030_5/simulation/__init__.py
ieee_2030_5/simulation/auth_context.py
ieee_2030_5/simulation/gridappsd_pump.py
ieee_2030_5/simulation/inverter.py
ieee_2030_5/types_/__init__.py
ieee_2030_5/utils/__init__.py
ieee_2030_5/utils/cryptography_wrapper.py
ieee_2030_5/utils/tls_wrapper.py
ieee_2030_5_gui/__init__.py
ieee_2030_5_gui/__main__.py
ieee_2030_5_gui/app_settings.py
ieee_2030_5_gui/der_programs.py
ieee_2030_5_gui/enddevices.py
ieee_2030_5_gui/init.py
ieee_2030_5_gui/main.py
ieee_2030_5_gui/orig_main.py
ieee_2030_5_gui/pages/__init__.py
ieee_2030_5_gui/pages/certs.py
ieee_2030_5_gui/pages/controls.py
ieee_2030_5_gui/pages/curves.py
gridappsd_2030_5-0.0.2a37.dist-info/entry_points.txt
gridappsd_2030_5-0.0.2a37.dist-info/LICENSE
gridappsd_2030_5-0.0.2a37.dist-info/WHEEL
gridappsd_2030_5-0.0.2a37.dist-info/METADATA
gridappsd_2030_5-0.0.2a37.dist-info/RECORD
