Metadata-Version: 2.1
Name: gridappsd-2030-5
Version: 0.0.2a37
Summary: 
Home-page: https://github.com/GRIDAPPSD/gridappsd-2030_5
License: BSD-3-Clause
Author: C. Allwardt
Author-email: 3979063+craig8@users.noreply.github.com
Maintainer: C. Allwardt
Maintainer-email: 3979063+craig8@users.noreply.github.com
Requires-Python: >=3.8.1,<4.0.0
Classifier: License :: OSI Approved :: BSD License
Classifier: Programming Language :: Python :: 3
Classifier: Programming Language :: Python :: 3.9
Classifier: Programming Language :: Python :: 3.10
Requires-Dist: Flask (>=2.0.3,<3.0.0)
Requires-Dist: blinker (>=1.5,<2.0)
Requires-Dist: click (>=8.1.3,<9.0.0)
Requires-Dist: cryptography (>=37.0.2,<38.0.0)
Requires-Dist: dataclasses-json (>=0.5.7,<0.6.0)
Requires-Dist: docutils (!=0.21)
Requires-Dist: flask-session (>=0.5.0,<0.6.0)
Requires-Dist: flask-talisman (>=1.0.0,<2.0.0)
Requires-Dist: flet (>=0.22.1,<0.23.0)
Requires-Dist: gevent (>=21.12.0,<22.0.0)
Requires-Dist: grequests (>=0.6.0,<0.7.0)
Requires-Dist: gridappsd-field-bus (==2024.8.1a1)
Requires-Dist: pickleDB (>=0.9.2,<0.10.0)
Requires-Dist: pyOpenSSL (>=22.0.0,<23.0.0)
Requires-Dist: pyyaml (>=6.0.1,<7.0.0)
Requires-Dist: simplekv (>=0.14.1,<0.15.0)
Requires-Dist: trio (>=0.21.0,<0.22.0)
Requires-Dist: tzlocal (>=4.2,<5.0)
Requires-Dist: xsdata[lxml] (>=22.5,<23.0)
Project-URL: Documentation, https://github.com/GRIDAPPSD/gridappsd-2030_5
Project-URL: Repository, https://github.com/GRIDAPPSD/gridappsd-2030_5
